odoo/addons/mass_mailing_multi_company/README.rst
odoo/addons/mass_mailing_multi_company/__init__.py
odoo/addons/mass_mailing_multi_company/__manifest__.py
odoo/addons/mass_mailing_multi_company/i18n/it.po
odoo/addons/mass_mailing_multi_company/i18n/mass_mailing_multi_company.pot
odoo/addons/mass_mailing_multi_company/models/__init__.py
odoo/addons/mass_mailing_multi_company/models/mailing_contact.py
odoo/addons/mass_mailing_multi_company/models/mailing_contact_subscription.py
odoo/addons/mass_mailing_multi_company/models/mailing_list.py
odoo/addons/mass_mailing_multi_company/models/mailing_mailing.py
odoo/addons/mass_mailing_multi_company/readme/CONTRIBUTORS.rst
odoo/addons/mass_mailing_multi_company/readme/DESCRIPTION.rst
odoo/addons/mass_mailing_multi_company/security/mass_mailing.xml
odoo/addons/mass_mailing_multi_company/static/description/icon.png
odoo/addons/mass_mailing_multi_company/static/description/index.html
odoo/addons/mass_mailing_multi_company/tests/__init__.py
odoo/addons/mass_mailing_multi_company/tests/test_mass_mailing_multi_company.py
odoo/addons/mass_mailing_multi_company/views/mailing_contact_views.xml
odoo/addons/mass_mailing_multi_company/views/mailing_list_views.xml
odoo/addons/mass_mailing_multi_company/views/mailing_mailing_views.xml
odoo_addon_mass_mailing_multi_company-16.0.1.0.0.4.dist-info/METADATA
odoo_addon_mass_mailing_multi_company-16.0.1.0.0.4.dist-info/WHEEL
odoo_addon_mass_mailing_multi_company-16.0.1.0.0.4.dist-info/top_level.txt
odoo_addon_mass_mailing_multi_company-16.0.1.0.0.4.dist-info/RECORD
