Metadata-Version: 2.1
Name: odoo-addon-mass_mailing_multi_company
Version: 16.0.1.0.0.4
Summary: Adds the company_id field to the models mailing.mailing, mailing.list and mailing.contact
Home-page: https://github.com/OCA/multi-company
Author: ForgeFlow S.L., Odoo Community Association (OCA)
Author-email: support@odoo-community.org
License: AGPL-3
Classifier: Programming Language :: Python
Classifier: Framework :: Odoo
Classifier: Framework :: Odoo :: 16.0
Classifier: License :: OSI Approved :: GNU Affero General Public License v3
Requires-Python: >=3.10
Requires-Dist: odoo<16.1dev,>=16.0a
